{
  "metadata": {
    "soundFile": "/home/nori/PycharmProjects/VRM-Puppet/web/temp/stream_1771842467_0.wav",
    "duration": 4.88
  },
  "mouthCues": [
    {
      "start": 0.0,
      "end": 0.16,
      "value": "X"
    },
    {
      "start": 0.16,
      "end": 0.36,
      "value": "B"
    },
    {
      "start": 0.36,
      "end": 0.43,
      "value": "A"
    },
    {
      "start": 0.43,
      "end": 0.5,
      "value": "C"
    },
    {
      "start": 0.5,
      "end": 0.56,
      "value": "A"
    },
    {
      "start": 0.56,
      "end": 0.73,
      "value": "C"
    },
    {
      "start": 0.73,
      "end": 0.8,
      "value": "B"
    },
    {
      "start": 0.8,
      "end": 0.94,
      "value": "G"
    },
    {
      "start": 0.94,
      "end": 1.01,
      "value": "C"
    },
    {
      "start": 1.01,
      "end": 1.08,
      "value": "B"
    },
    {
      "start": 1.08,
      "end": 1.15,
      "value": "F"
    },
    {
      "start": 1.15,
      "end": 1.22,
      "value": "B"
    },
    {
      "start": 1.22,
      "end": 1.43,
      "value": "C"
    },
    {
      "start": 1.43,
      "end": 1.5,
      "value": "B"
    },
    {
      "start": 1.5,
      "end": 1.64,
      "value": "F"
    },
    {
      "start": 1.64,
      "end": 1.71,
      "value": "B"
    },
    {
      "start": 1.71,
      "end": 1.92,
      "value": "C"
    },
    {
      "start": 1.92,
      "end": 1.99,
      "value": "H"
    },
    {
      "start": 1.99,
      "end": 2.34,
      "value": "B"
    },
    {
      "start": 2.34,
      "end": 2.48,
      "value": "F"
    },
    {
      "start": 2.48,
      "end": 2.62,
      "value": "B"
    },
    {
      "start": 2.62,
      "end": 2.81,
      "value": "X"
    },
    {
      "start": 2.81,
      "end": 3.12,
      "value": "B"
    },
    {
      "start": 3.12,
      "end": 3.47,
      "value": "F"
    },
    {
      "start": 3.47,
      "end": 3.61,
      "value": "B"
    },
    {
      "start": 3.61,
      "end": 3.69,
      "value": "A"
    },
    {
      "start": 3.69,
      "end": 3.76,
      "value": "C"
    },
    {
      "start": 3.76,
      "end": 3.97,
      "value": "B"
    },
    {
      "start": 3.97,
      "end": 4.04,
      "value": "G"
    },
    {
      "start": 4.04,
      "end": 4.11,
      "value": "C"
    },
    {
      "start": 4.11,
      "end": 4.25,
      "value": "B"
    },
    {
      "start": 4.25,
      "end": 4.33,
      "value": "A"
    },
    {
      "start": 4.33,
      "end": 4.53,
      "value": "C"
    },
    {
      "start": 4.53,
      "end": 4.81,
      "value": "E"
    },
    {
      "start": 4.81,
      "end": 4.88,
      "value": "X"
    }
  ]
}