{
  "metadata": {
    "soundFile": "/home/nori/PycharmProjects/VRM-Puppet/web/temp/stream_1771849414_0.wav",
    "duration": 9.04
  },
  "mouthCues": [
    {
      "start": 0.0,
      "end": 0.2,
      "value": "X"
    },
    {
      "start": 0.2,
      "end": 0.31,
      "value": "B"
    },
    {
      "start": 0.31,
      "end": 0.94,
      "value": "H"
    },
    {
      "start": 0.94,
      "end": 1.04,
      "value": "A"
    },
    {
      "start": 1.04,
      "end": 1.12,
      "value": "C"
    },
    {
      "start": 1.12,
      "end": 1.2,
      "value": "A"
    },
    {
      "start": 1.2,
      "end": 1.42,
      "value": "B"
    },
    {
      "start": 1.42,
      "end": 1.7,
      "value": "F"
    },
    {
      "start": 1.7,
      "end": 2.05,
      "value": "B"
    },
    {
      "start": 2.05,
      "end": 2.12,
      "value": "H"
    },
    {
      "start": 2.12,
      "end": 2.19,
      "value": "C"
    },
    {
      "start": 2.19,
      "end": 2.26,
      "value": "B"
    },
    {
      "start": 2.26,
      "end": 2.33,
      "value": "A"
    },
    {
      "start": 2.33,
      "end": 2.4,
      "value": "C"
    },
    {
      "start": 2.4,
      "end": 2.56,
      "value": "A"
    },
    {
      "start": 2.56,
      "end": 2.83,
      "value": "E"
    },
    {
      "start": 2.83,
      "end": 2.9,
      "value": "F"
    },
    {
      "start": 2.9,
      "end": 3.25,
      "value": "E"
    },
    {
      "start": 3.25,
      "end": 3.32,
      "value": "B"
    },
    {
      "start": 3.32,
      "end": 3.4,
      "value": "A"
    },
    {
      "start": 3.4,
      "end": 3.47,
      "value": "C"
    },
    {
      "start": 3.47,
      "end": 3.54,
      "value": "B"
    },
    {
      "start": 3.54,
      "end": 3.75,
      "value": "C"
    },
    {
      "start": 3.75,
      "end": 3.82,
      "value": "B"
    },
    {
      "start": 3.82,
      "end": 3.96,
      "value": "G"
    },
    {
      "start": 3.96,
      "end": 4.1,
      "value": "C"
    },
    {
      "start": 4.1,
      "end": 4.17,
      "value": "B"
    },
    {
      "start": 4.17,
      "end": 4.36,
      "value": "F"
    },
    {
      "start": 4.36,
      "end": 4.41,
      "value": "E"
    },
    {
      "start": 4.41,
      "end": 4.8,
      "value": "C"
    },
    {
      "start": 4.8,
      "end": 4.94,
      "value": "E"
    },
    {
      "start": 4.94,
      "end": 5.52,
      "value": "B"
    },
    {
      "start": 5.52,
      "end": 5.79,
      "value": "C"
    },
    {
      "start": 5.79,
      "end": 5.89,
      "value": "A"
    },
    {
      "start": 5.89,
      "end": 5.97,
      "value": "D"
    },
    {
      "start": 5.97,
      "end": 6.04,
      "value": "C"
    },
    {
      "start": 6.04,
      "end": 6.18,
      "value": "B"
    },
    {
      "start": 6.18,
      "end": 6.32,
      "value": "D"
    },
    {
      "start": 6.32,
      "end": 6.39,
      "value": "C"
    },
    {
      "start": 6.39,
      "end": 6.47,
      "value": "A"
    },
    {
      "start": 6.47,
      "end": 6.6,
      "value": "C"
    },
    {
      "start": 6.6,
      "end": 6.81,
      "value": "B"
    },
    {
      "start": 6.81,
      "end": 7.11,
      "value": "X"
    },
    {
      "start": 7.11,
      "end": 7.16,
      "value": "B"
    },
    {
      "start": 7.16,
      "end": 7.35,
      "value": "F"
    },
    {
      "start": 7.35,
      "end": 7.42,
      "value": "E"
    },
    {
      "start": 7.42,
      "end": 7.77,
      "value": "D"
    },
    {
      "start": 7.77,
      "end": 7.91,
      "value": "B"
    },
    {
      "start": 7.91,
      "end": 8.19,
      "value": "E"
    },
    {
      "start": 8.19,
      "end": 8.4,
      "value": "F"
    },
    {
      "start": 8.4,
      "end": 8.61,
      "value": "B"
    },
    {
      "start": 8.61,
      "end": 9.04,
      "value": "X"
    }
  ]
}